cardano_pool_checker/__init__.py
cardano_pool_checker/__main__.py
cardano_pool_checker/cardano_pool_checker_class.py
cardano_pool_checker/cardano_pool_checker_config.py
cardano_pool_checker/pools/pools_dns_translations.json
cardano_pool_checker/pools/pools_list.json
cardano_pool_checker/pools/pools_register.json
cardano_pool_checker/pools/pools_updates.json
cardano_pool_checker/pools/registered_currently_sharing_meta_json_homepage.json
cardano_pool_checker/pools/registered_currently_sharing_meta_url.json
cardano_pool_checker/pools/registered_currently_sharing_owners.json
cardano_pool_checker/pools/registered_currently_sharing_relay_hostname.json
cardano_pool_checker/pools/registered_currently_sharing_relay_ipv4.json
cardano_pool_checker/pools/registered_currently_sharing_relay_ipv6.json
cardano_pool_checker/pools/registered_currently_sharing_reward_addr.json
cardano_pool_checker/pools/registered_multi_stake_pool_operators.json
cardano_pool_checker/pools/registered_sharing_meta_json_homepage.json
cardano_pool_checker/pools/registered_sharing_meta_url.json
cardano_pool_checker/pools/registered_sharing_owners.json
cardano_pool_checker/pools/registered_sharing_relay_hostname.json
cardano_pool_checker/pools/registered_sharing_relay_ipv4.json
cardano_pool_checker/pools/registered_sharing_relay_ipv6.json
cardano_pool_checker/pools/registered_sharing_reward_addr.json
cardano_pool_checker/pools/registered_single_stake_pool_operators.json
cardano_pool_checker/py.typed
cardano_pool_checker-1.0.0.dist-info/LICENSE
cardano_pool_checker-1.0.0.dist-info/METADATA
cardano_pool_checker-1.0.0.dist-info/WHEEL
cardano_pool_checker-1.0.0.dist-info/entry_points.txt
cardano_pool_checker-1.0.0.dist-info/RECORD
