Metadata-Version: 2.1
Name: cardano-pool-checker
Version: 1.0.0
Summary: JSON-based collection of historical Cardano stake pool registration data, lists of multi pool operators by different criteria and associated maintenance tools.
License: GPL-3.0
Author: Josep M Homs
Author-email: jmhoms@gmail.com
Requires-Python: >=3.10,<4.0
Classifier: License :: OSI Approved :: GNU General Public License v3 (GPLv3)
Classifier: Programming Language :: Python :: 3
Classifier: Programming Language :: Python :: 3.10
Classifier: Programming Language :: Python :: 3.11
Requires-Dist: dnspython (>=2.3.0,<3.0.0)
Requires-Dist: ipaddress (>=1.0.23,<2.0.0)
Requires-Dist: urllib3 (>=2.0.6,<3.0.0)
Requires-Dist: validators (>=0.22.0,<0.23.0)
